promptlab/__init__.py
promptlab/_cli.py
promptlab/_experiment.py
promptlab/_logging.py
promptlab/_utils.py
promptlab/asset.py
promptlab/core.py
promptlab/enums.py
promptlab/types.py
promptlab/evaluator/__init__.py
promptlab/evaluator/bleu.py
promptlab/evaluator/coherence.py
promptlab/evaluator/evaluator.py
promptlab/evaluator/evaluator_factory.py
promptlab/evaluator/exact_match.py
promptlab/evaluator/f1_score.py
promptlab/evaluator/faithfulness.py
promptlab/evaluator/fluency.py
promptlab/evaluator/groundedness.py
promptlab/evaluator/harmful_content.py
promptlab/evaluator/relevance.py
promptlab/evaluator/rouge.py
promptlab/evaluator/similarity.py
promptlab/model/__init__.py
promptlab/model/azure_openai.py
promptlab/model/deepseek.py
promptlab/model/model.py
promptlab/model/model_factory.py
promptlab/model/ollama.py
promptlab/model/openrouter.py
promptlab/sqlite/__init__.py
promptlab/sqlite/models.py
promptlab/sqlite/session.py
promptlab/sqlite/sql.py
promptlab/studio/__init__.py
promptlab/studio/studio.py
promptlab/studio/studio_api.py
promptlab/tracer/__init__.py
promptlab/tracer/api_tracer.py
promptlab/tracer/local_tracer.py
promptlab/tracer/tracer.py
promptlab/tracer/tracer_factory.py
promptlab/web/__init__.py
promptlab/web/index.html
promptlab-0.1.10.dist-info/LICENSE
promptlab-0.1.10.dist-info/METADATA
promptlab-0.1.10.dist-info/WHEEL
promptlab-0.1.10.dist-info/entry_points.txt
promptlab-0.1.10.dist-info/top_level.txt
promptlab-0.1.10.dist-info/RECORD
