Metadata-Version: 2.1
Name: promptlab
Version: 0.1.10
Summary: PromptLab is a free, lightweight, open-source experimentation tool for Gen AI applications.
Author-email: ra1han <hello@pl.com>
License: MIT License
Project-URL: Homepage, https://github.com/imum-ai/promptlab
Project-URL: Issues, https://github.com/imum-ai/promptlab/issues
Classifier: Programming Language :: Python :: 3
Classifier: License :: OSI Approved :: MIT License
Classifier: Operating System :: OS Independent
Requires-Python: >=3.8
License-File: LICENSE
Requires-Dist: pydantic>=2.0.0
Requires-Dist: requests>=2.25.0
Requires-Dist: openai>=1.60.0
Requires-Dist: flask[async]>=3.0.0
Requires-Dist: flask-cors>=5.0.0
Requires-Dist: click>=8.0.0
Requires-Dist: ollama>=0.4.7
Requires-Dist: aiohttp>=3.8.0
Requires-Dist: fastapi>=0.100.0
Requires-Dist: numpy
Requires-Dist: python-dotenv>=1.0.0
Requires-Dist: rouge-score>=0.1.2
Requires-Dist: art>=6.5
Requires-Dist: setuptools
Requires-Dist: fastapi
Requires-Dist: uvicorn[standard]>=0.18.0
Requires-Dist: sqlalchemy
Requires-Dist: passlib
Requires-Dist: python-jose
Requires-Dist: python-multipart
Requires-Dist: bcrypt
Requires-Dist: uvloop>=0.17.0; sys_platform != "win32"
Requires-Dist: httptools>=0.5.0; sys_platform != "win32"
